pulp_glue/console/__init__.py
pulp_glue/console/context.py
pulp_glue_console-0.1.5.dev0.dist-info/METADATA
pulp_glue_console-0.1.5.dev0.dist-info/WHEEL
pulp_glue_console-0.1.5.dev0.dist-info/top_level.txt
pulp_glue_console-0.1.5.dev0.dist-info/RECORD
