Metadata-Version: 2.1
Name: pulp-glue-console
Version: 0.1.5.dev0
Summary: Version agnostic glue library to talk to pulpcore's REST API. (Console plugin)
Author-email: Pulp Team <pulp-list@redhat.com>
License: GPLv2+
Project-URL: repository, https://github.com/pulp/pulp-cli-console
Project-URL: changelog, https://github.com/pulp/pulp-cli-console/blob/main/CHANGES.md
Classifier: Development Status :: 4 - Beta
Classifier: Environment :: Other Environment
Classifier: Intended Audience :: Developers
Classifier: License :: OSI Approved :: GNU General Public License v2 or later (GPLv2+)
Classifier: Operating System :: OS Independent
Classifier: Programming Language :: Python :: 3
Classifier: Topic :: System :: Software Distribution
Classifier: Typing :: Typed
Requires-Python: >=3.8
Requires-Dist: pulp-glue<0.36,>=0.23.1
